jira_insight/__init__.py
jira_insight/insight.py
jira_insight-0.6.1.dist-info/LICENSE
jira_insight-0.6.1.dist-info/METADATA
jira_insight-0.6.1.dist-info/WHEEL
jira_insight-0.6.1.dist-info/top_level.txt
jira_insight-0.6.1.dist-info/RECORD
