Metadata-Version: 2.1
Name: jira-insight
Version: 0.6.1
Summary: API client for the Insight app for Jira
Home-page: https://github.com/dstengele/python-insight
Author: Dennis Stengele
Author-email: dennis@stengele.me
License: UNKNOWN
Platform: UNKNOWN
Classifier: Programming Language :: Python :: 3
Classifier: License :: OSI Approved :: GNU General Public License v3 (GPLv3)
Classifier: Operating System :: OS Independent
Requires-Python: >=3.6
License-File: LICENSE
Requires-Dist: lazy
Requires-Dist: requests
Provides-Extra: oauth
Requires-Dist: oauthlib ; extra == 'oauth'
Requires-Dist: requests-oauthlib ; extra == 'oauth'
